alp_graphblas-0.8.41.dist-info/RECORD
alp_graphblas-0.8.41.dist-info/WHEEL
alp_graphblas-0.8.41.dist-info/top_level.txt
alp_graphblas-0.8.41.dist-info/METADATA
pyalp/__init__.py
pyalp/pyalp_ref.cpython-39-darwin.so
pyalp/.dylibs/libomp.dylib
pyalp/.dylibs/libgraphblas.0.7.0.dylib
