Metadata-Version: 2.4
Name: alp-graphblas
Version: 0.8.41
Summary: Python bindings for ALP GraphBLAS (minimal package layout)
Author: ALP
License: Apache-2.0
Requires-Python: >=3.8
Requires-Dist: numpy>=1.22
